quart_peewee.py
quart_peewee-0.1.1.dist-info/LICENSE
quart_peewee-0.1.1.dist-info/METADATA
quart_peewee-0.1.1.dist-info/WHEEL
quart_peewee-0.1.1.dist-info/RECORD
