Metadata-Version: 2.1
Name: quart-peewee
Version: 0.1.1
Summary: Integration between the Quart web framework and the Peewee ORM through the Peewee-AIO
Home-page: https://github.com/Mystic-Mirage/quart-peewee
License: MIT
Keywords: peewee,quart,asyncio,trio,orm
Author: Mystic-Mirage
Author-email: mm@m10e.net
Requires-Python: >=3.8,<4.0
Classifier: Development Status :: 3 - Alpha
Classifier: Intended Audience :: Developers
Classifier: License :: OSI Approved :: MIT License
Classifier: Programming Language :: Python
Classifier: Programming Language :: Python :: 3
Classifier: Programming Language :: Python :: 3.8
Classifier: Programming Language :: Python :: 3.9
Classifier: Programming Language :: Python :: 3.10
Classifier: Programming Language :: Python :: 3.11
Classifier: Programming Language :: Python :: 3.12
Requires-Dist: peewee-aio (>=1.3.0)
Requires-Dist: quart (>=0.19.1)
Project-URL: Repository, https://github.com/Mystic-Mirage/quart-peewee
